dispatch/__init__.py
dispatch/dispatch.py
dispatch_generic-1.0.1.dist-info/licenses/LICENSE
dispatch_generic-1.0.1.dist-info/METADATA
dispatch_generic-1.0.1.dist-info/WHEEL
dispatch_generic-1.0.1.dist-info/top_level.txt
dispatch_generic-1.0.1.dist-info/RECORD
