Metadata-Version: 2.4
Name: dispatch-generic
Version: 1.0.1
Summary: A simple dispatch decorator for generic functions
Author-email: HarryLHW <123lhw321@gmail.com>
License-Expression: MIT
Project-URL: Homepage, https://github.com/HarryLHW/dispatch-generic
Project-URL: Issues, https://github.com/HarryLHW/dispatch-generic/issues
Classifier: Programming Language :: Python :: 3
Classifier: Operating System :: OS Independent
Requires-Python: >=3.9
License-File: LICENSE
Requires-Dist: typeguard>=4.4.2
Dynamic: license-file
